dutch_words/__init__.py
dutch_words/dutch10000-utf8.txt
dutch_words-0.2.5.dist-info/WHEEL
dutch_words-0.2.5.dist-info/METADATA
dutch_words-0.2.5.dist-info/RECORD
