Metadata-Version: 2.1
Name: dutch-words
Version: 0.2.5
Summary: 
Home-page: https://github.com/leukeleu/dutch-words
License: CC-BY-4.0
Author: Ramon de Jezus
Author-email: rdejezus@leukeleu.nl
Requires-Python: >=3.6,<4.0
Classifier: License :: Other/Proprietary License
Classifier: Programming Language :: Python :: 3
Classifier: Programming Language :: Python :: 3.6
Classifier: Programming Language :: Python :: 3.7
Classifier: Programming Language :: Python :: 3.8
Project-URL: Repository, https://github.com/leukeleu/dutch-words
